scrippy_remote/__init__.py
scrippy_remote/cifs/__init__.py
scrippy_remote/ftp/__init__.py
scrippy_remote/ftp/clients/__init__.py
scrippy_remote/ftp/clients/errors/__init__.py
scrippy_remote/ftp/clients/ftp/__init__.py
scrippy_remote/ftp/clients/ftpes/__init__.py
scrippy_remote/ftp/clients/ftps/__init__.py
scrippy_remote/local/__init__.py
scrippy_remote/ssh/__init__.py
scrippy_remote-3.0.4.dist-info/licenses/LICENSE
scrippy_remote-3.0.4.dist-info/METADATA
scrippy_remote-3.0.4.dist-info/WHEEL
scrippy_remote-3.0.4.dist-info/top_level.txt
scrippy_remote-3.0.4.dist-info/RECORD
